{"meta": {"rows": 1, "source": "tidb"}, "data": [{"kpi": {"total_victims": 23484, "domestic_cases": 1079, "avg_age": 46.26383920967467}, "demographics": [{"age_num": 4.0, "sex_code": "F", "count": 4}, {"age_num": 4.0, "sex_code": "M", "count": 2}, {"age_num": 5.0, "sex_code": "M", "count": 4}, {"age_num": 5.0, "sex_code": "F", "count": 3}, {"age_num": 6.0, "sex_code": "F", "count": 4}, {"age_num": 6.0, "sex_code": "M", "count": 2}, {"age_num": 7.0, "sex_code": "F", "count": 7}, {"age_num": 7.0, "sex_code": "M", "count": 5}, {"age_num": 8.0, "sex_code": "M", "count": 2}, {"age_num": 9.0, "sex_code": "M", "count": 3}, {"age_num": 9.0, "sex_code": "F", "count": 5}, {"age_num": 10.0, "sex_code": "F", "count": 5}, {"age_num": 11.0, "sex_code": "M", "count": 4}, {"age_num": 11.0, "sex_code": "F", "count": 2}, {"age_num": 12.0, "sex_code": "F", "count": 5}, {"age_num": 12.0, "sex_code": "M", "count": 4}, {"age_num": 13.0, "sex_code": "M", "count": 10}, {"age_num": 13.0, "sex_code": "F", "count": 8}, {"age_num": 14.0, "sex_code": "M", "count": 16}, {"age_num": 14.0, "sex_code": "F", "count": 11}, {"age_num": 15.0, "sex_code": "M", "count": 31}, {"age_num": 15.0, "sex_code": "F", "count": 15}, {"age_num": 16.0, "sex_code": "F", "count": 45}, {"age_num": 16.0, "sex_code": "M", "count": 40}, {"age_num": 17.0, "sex_code": "M", "count": 55}, {"age_num": 17.0, "sex_code": "F", "count": 55}, {"age_num": 18.0, "sex_code": "F", "count": 134}, {"age_num": 18.0, "sex_code": "M", "count": 127}, {"age_num": 19.0, "sex_code": "M", "count": 149}, {"age_num": 19.0, "sex_code": "F", "count": 175}, {"age_num": 20.0, "sex_code": "F", "count": 223}, {"age_num": 20.0, "sex_code": "M", "count": 158}, {"age_num": 21.0, "sex_code": "M", "count": 159}, {"age_num": 21.0, "sex_code": "F", "count": 224}, {"age_num": 22.0, "sex_code": "M", "count": 202}, {"age_num": 22.0, "sex_code": "F", "count": 243}, {"age_num": 23.0, "sex_code": "M", "count": 224}, {"age_num": 23.0, "sex_code": "F", "count": 232}, {"age_num": 24.0, "sex_code": "F", "count": 273}, {"age_num": 24.0, "sex_code": "M", "count": 200}, {"age_num": 25.0, "sex_code": "M", "count": 206}, {"age_num": 25.0, "sex_code": "F", "count": 255}, {"age_num": 26.0, "sex_code": "M", "count": 210}, {"age_num": 26.0, "sex_code": "F", "count": 243}, {"age_num": 27.0, "sex_code": "M", "count": 259}, {"age_num": 27.0, "sex_code": "F", "count": 271}, {"age_num": 28.0, "sex_code": "M", "count": 227}, {"age_num": 28.0, "sex_code": "F", "count": 249}, {"age_num": 29.0, "sex_code": "M", "count": 253}, {"age_num": 29.0, "sex_code": "F", "count": 272}, {"age_num": 30.0, "sex_code": "F", "count": 268}, {"age_num": 30.0, "sex_code": "M", "count": 254}, {"age_num": 31.0, "sex_code": "F", "count": 264}, {"age_num": 31.0, "sex_code": "M", "count": 253}, {"age_num": 32.0, "sex_code": "F", "count": 276}, {"age_num": 32.0, "sex_code": "M", "count": 235}, {"age_num": 33.0, "sex_code": "F", "count": 258}, {"age_num": 33.0, "sex_code": "M", "count": 242}, {"age_num": 34.0, "sex_code": "M", "count": 217}, {"age_num": 34.0, "sex_code": "F", "count": 221}, {"age_num": 35.0, "sex_code": "M", "count": 259}, {"age_num": 35.0, "sex_code": "F", "count": 234}, {"age_num": 36.0, "sex_code": "F", "count": 210}, {"age_num": 36.0, "sex_code": "M", "count": 232}, {"age_num": 37.0, "sex_code": "F", "count": 234}, {"age_num": 37.0, "sex_code": "M", "count": 227}, {"age_num": 38.0, "sex_code": "M", "count": 212}, {"age_num": 38.0, "sex_code": "F", "count": 220}, {"age_num": 39.0, "sex_code": "F", "count": 218}, {"age_num": 39.0, "sex_code": "M", "count": 235}, {"age_num": 40.0, "sex_code": "F", "count": 183}, {"age_num": 40.0, "sex_code": "M", "count": 234}, {"age_num": 41.0, "sex_code": "M", "count": 171}, {"age_num": 41.0, "sex_code": "F", "count": 205}, {"age_num": 42.0, "sex_code": "F", "count": 212}, {"age_num": 42.0, "sex_code": "M", "count": 202}, {"age_num": 43.0, "sex_code": "F", "count": 166}, {"age_num": 43.0, "sex_code": "M", "count": 197}, {"age_num": 44.0, "sex_code": "F", "count": 205}, {"age_num": 44.0, "sex_code": "M", "count": 204}, {"age_num": 45.0, "sex_code": "M", "count": 206}, {"age_num": 45.0, "sex_code": "F", "count": 175}, {"age_num": 46.0, "sex_code": "M", "count": 164}, {"age_num": 46.0, "sex_code": "F", "count": 146}, {"age_num": 47.0, "sex_code": "F", "count": 149}, {"age_num": 47.0, "sex_code": "M", "count": 161}, {"age_num": 48.0, "sex_code": "M", "count": 167}, {"age_num": 48.0, "sex_code": "F", "count": 156}, {"age_num": 49.0, "sex_code": "M", "count": 171}, {"age_num": 49.0, "sex_code": "F", "count": 164}, {"age_num": 50.0, "sex_code": "F", "count": 150}, {"age_num": 50.0, "sex_code": "M", "count": 172}, {"age_num": 51.0, "sex_code": "F", "count": 155}, {"age_num": 51.0, "sex_code": "M", "count": 162}, {"age_num": 52.0, "sex_code": "M", "count": 141}, {"age_num": 52.0, "sex_code": "F", "count": 154}, {"age_num": 53.0, "sex_code": "M", "count": 158}, {"age_num": 53.0, "sex_code": "F", "count": 157}, {"age_num": 54.0, "sex_code": "M", "count": 148}, {"age_num": 54.0, "sex_code": "F", "count": 157}, {"age_num": 55.0, "sex_code": "F", "count": 155}, {"age_num": 55.0, "sex_code": "M", "count": 161}, {"age_num": 56.0, "sex_code": "F", "count": 159}, {"age_num": 56.0, "sex_code": "M", "count": 168}, {"age_num": 57.0, "sex_code": "M", "count": 159}, {"age_num": 57.0, "sex_code": "F", "count": 140}, {"age_num": 58.0, "sex_code": "F", "count": 141}, {"age_num": 58.0, "sex_code": "M", "count": 190}, {"age_num": 59.0, "sex_code": "F", "count": 150}, {"age_num": 59.0, "sex_code": "M", "count": 159}, {"age_num": 60.0, "sex_code": "M", "count": 160}, {"age_num": 60.0, "sex_code": "F", "count": 153}, {"age_num": 61.0, "sex_code": "M", "count": 173}, {"age_num": 61.0, "sex_code": "F", "count": 172}, {"age_num": 62.0, "sex_code": "M", "count": 173}, {"age_num": 62.0, "sex_code": "F", "count": 183}, {"age_num": 63.0, "sex_code": "M", "count": 171}, {"age_num": 63.0, "sex_code": "F", "count": 159}, {"age_num": 64.0, "sex_code": "F", "count": 172}, {"age_num": 64.0, "sex_code": "M", "count": 116}, {"age_num": 65.0, "sex_code": "F", "count": 147}, {"age_num": 65.0, "sex_code": "M", "count": 154}, {"age_num": 66.0, "sex_code": "F", "count": 154}, {"age_num": 66.0, "sex_code": "M", "count": 144}, {"age_num": 67.0, "sex_code": "F", "count": 153}, {"age_num": 67.0, "sex_code": "M", "count": 116}, {"age_num": 68.0, "sex_code": "F", "count": 134}, {"age_num": 68.0, "sex_code": "M", "count": 118}, {"age_num": 69.0, "sex_code": "M", "count": 120}, {"age_num": 69.0, "sex_code": "F", "count": 137}, {"age_num": 70.0, "sex_code": "M", "count": 109}, {"age_num": 70.0, "sex_code": "F", "count": 135}, {"age_num": 71.0, "sex_code": "F", "count": 137}, {"age_num": 71.0, "sex_code": "M", "count": 101}, {"age_num": 72.0, "sex_code": "F", "count": 129}, {"age_num": 72.0, "sex_code": "M", "count": 108}, {"age_num": 73.0, "sex_code": "F", "count": 132}, {"age_num": 73.0, "sex_code": "M", "count": 88}, {"age_num": 74.0, "sex_code": "M", "count": 94}, {"age_num": 74.0, "sex_code": "F", "count": 132}, {"age_num": 75.0, "sex_code": "M", "count": 88}, {"age_num": 75.0, "sex_code": "F", "count": 131}, {"age_num": 76.0, "sex_code": "M", "count": 77}, {"age_num": 76.0, "sex_code": "F", "count": 97}, {"age_num": 77.0, "sex_code": "F", "count": 105}, {"age_num": 77.0, "sex_code": "M", "count": 73}, {"age_num": 78.0, "sex_code": "F", "count": 102}, {"age_num": 78.0, "sex_code": "M", "count": 80}, {"age_num": 79.0, "sex_code": "F", "count": 101}, {"age_num": 79.0, "sex_code": "M", "count": 73}, {"age_num": 80.0, "sex_code": "F", "count": 97}, {"age_num": 80.0, "sex_code": "M", "count": 76}, {"age_num": 81.0, "sex_code": "M", "count": 61}, {"age_num": 81.0, "sex_code": "F", "count": 101}, {"age_num": 82.0, "sex_code": "F", "count": 74}, {"age_num": 82.0, "sex_code": "M", "count": 52}, {"age_num": 83.0, "sex_code": "F", "count": 61}, {"age_num": 83.0, "sex_code": "M", "count": 53}, {"age_num": 84.0, "sex_code": "M", "count": 37}, {"age_num": 84.0, "sex_code": "F", "count": 72}, {"age_num": 85.0, "sex_code": "F", "count": 61}, {"age_num": 85.0, "sex_code": "M", "count": 39}, {"age_num": 86.0, "sex_code": "M", "count": 36}, {"age_num": 86.0, "sex_code": "F", "count": 58}, {"age_num": 87.0, "sex_code": "F", "count": 51}, {"age_num": 87.0, "sex_code": "M", "count": 32}, {"age_num": 88.0, "sex_code": "F", "count": 39}, {"age_num": 88.0, "sex_code": "M", "count": 34}, {"age_num": 89.0, "sex_code": "F", "count": 37}, {"age_num": 89.0, "sex_code": "M", "count": 16}, {"age_num": 90.0, "sex_code": "F", "count": 34}, {"age_num": 90.0, "sex_code": "M", "count": 12}, {"age_num": 91.0, "sex_code": "M", "count": 16}, {"age_num": 91.0, "sex_code": "F", "count": 23}, {"age_num": 92.0, "sex_code": "M", "count": 16}, {"age_num": 92.0, "sex_code": "F", "count": 16}, {"age_num": 93.0, "sex_code": "M", "count": 7}, {"age_num": 93.0, "sex_code": "F", "count": 17}, {"age_num": 94.0, "sex_code": "M", "count": 7}, {"age_num": 94.0, "sex_code": "F", "count": 13}, {"age_num": 95.0, "sex_code": "M", "count": 6}, {"age_num": 95.0, "sex_code": "F", "count": 8}, {"age_num": 96.0, "sex_code": "M", "count": 2}, {"age_num": 96.0, "sex_code": "F", "count": 13}, {"age_num": 97.0, "sex_code": "F", "count": 7}, {"age_num": 97.0, "sex_code": "M", "count": 1}, {"age_num": 98.0, "sex_code": "M", "count": 5}, {"age_num": 98.0, "sex_code": "F", "count": 4}, {"age_num": 99.0, "sex_code": "M", "count": 22}, {"age_num": 99.0, "sex_code": "F", "count": 9}], "relationships": [{"RELATIONSHIP_NAME": "Victim Was Stranger", "count": 11053}, {"RELATIONSHIP_NAME": "Victim Was Acquaintance", "count": 2960}, {"RELATIONSHIP_NAME": "Victim was Otherwise Known", "count": 2732}, {"RELATIONSHIP_NAME": "Victim Was Ex-Relationship (Ex-Boyfriend/Girlfriend)", "count": 1167}, {"RELATIONSHIP_NAME": "Victim Was Parent", "count": 869}, {"RELATIONSHIP_NAME": "Victim Was Friend", "count": 782}, {"RELATIONSHIP_NAME": "Victim Was Other Family Member", "count": 721}, {"RELATIONSHIP_NAME": "Victim Was Sibling", "count": 548}, {"RELATIONSHIP_NAME": "Victim Was Boyfriend/Girlfriend", "count": 545}, {"RELATIONSHIP_NAME": "Victim was Employer", "count": 309}], "activity_heatmap": [{"activity": "Responding to Disturbance Call", "offense_category": "Fraud Offenses", "count": 26}, {"activity": null, "offense_category": "Fraud Offenses", "count": 23380}, {"activity": "Traffic Pursuits and Stops", "offense_category": "Fraud Offenses", "count": 9}, {"activity": "Handling, Transporting, Custody of Prisoners", "offense_category": "Fraud Offenses", "count": 12}, {"activity": "All Other", "offense_category": "Fraud Offenses", "count": 8}, {"activity": "Attempting Other Arrests", "offense_category": "Fraud Offenses", "count": 24}, {"activity": "Robberies in Progress or Pursuing Robbery Suspects", "offense_category": "Fraud Offenses", "count": 5}, {"activity": "Investigating Suspicious Persons or Circumstances", "offense_category": "Fraud Offenses", "count": 19}, {"activity": "Burglaries in Progress or Pursuing Burglary Suspects", "offense_category": "Fraud Offenses", "count": 1}], "raw_sample": [{"victim_id": 158023797, "vic_incident_id": 143432439, "victim_type_id": 4, "activity_type_id": NaN, "age_num": 50.0, "sex_code": "M", "data_year": 2021, "INCIDENT_ID": 143432439, "INCIDENT_DATE": "2021-08-01", "VICTIM_TYPE_NAME": "Individual", "RELATIONSHIP_NAME": "Victim Was Stranger", "victim_activity_at_incident": null, "offense_type_id": NaN, "offense_category_name": "Fraud Offenses", "offense_code": "26A"}, {"victim_id": 195176512, "vic_incident_id": 175910401, "victim_type_id": 4, "activity_type_id": NaN, "age_num": 40.0, "sex_code": "M", "data_year": 2023, "INCIDENT_ID": 175910401, "INCIDENT_DATE": "2023-02-23", "VICTIM_TYPE_NAME": "Individual", "RELATIONSHIP_NAME": "Victim Was Stranger", "victim_activity_at_incident": null, "offense_type_id": NaN, "offense_category_name": "Fraud Offenses", "offense_code": "26F"}, {"victim_id": 163263132, "vic_incident_id": 148021261, "victim_type_id": 4, "activity_type_id": NaN, "age_num": 71.0, "sex_code": "F", "data_year": 2021, "INCIDENT_ID": 148021261, "INCIDENT_DATE": "2021-07-15", "VICTIM_TYPE_NAME": "Individual", "RELATIONSHIP_NAME": "Victim Was Stranger", "victim_activity_at_incident": null, "offense_type_id": NaN, "offense_category_name": "Fraud Offenses", "offense_code": "26A"}, {"victim_id": 216950366, "vic_incident_id": 194907884, "victim_type_id": 4, "activity_type_id": NaN, "age_num": 44.0, "sex_code": "M", "data_year": 2024, "INCIDENT_ID": 194907884, "INCIDENT_DATE": "2024-07-30", "VICTIM_TYPE_NAME": "Individual", "RELATIONSHIP_NAME": "Victim Was Stranger", "victim_activity_at_incident": null, "offense_type_id": NaN, "offense_category_name": "Fraud Offenses", "offense_code": "26A"}, {"victim_id": 201581914, "vic_incident_id": 181527747, "victim_type_id": 4, "activity_type_id": NaN, "age_num": 34.0, "sex_code": "M", "data_year": 2023, "INCIDENT_ID": 181527747, "INCIDENT_DATE": "2023-11-22", "VICTIM_TYPE_NAME": "Individual", "RELATIONSHIP_NAME": "Victim Was Stranger", "victim_activity_at_incident": null, "offense_type_id": NaN, "offense_category_name": "Fraud Offenses", "offense_code": "26A"}, {"victim_id": 158014001, "vic_incident_id": 143423524, "victim_type_id": 4, "activity_type_id": NaN, "age_num": 66.0, "sex_code": "F", "data_year": 2021, "INCIDENT_ID": 143423524, "INCIDENT_DATE": "2021-02-28", "VICTIM_TYPE_NAME": "Individual", "RELATIONSHIP_NAME": "Victim Was Stranger", "victim_activity_at_incident": null, "offense_type_id": NaN, "offense_category_name": "Fraud Offenses", "offense_code": "26A"}, {"victim_id": 190492681, "vic_incident_id": 171822979, "victim_type_id": 4, "activity_type_id": NaN, "age_num": 27.0, "sex_code": "M", "data_year": 2023, "INCIDENT_ID": 171822979, "INCIDENT_DATE": "2023-02-17", "VICTIM_TYPE_NAME": "Individual", "RELATIONSHIP_NAME": "Victim Was Stranger", "victim_activity_at_incident": null, "offense_type_id": NaN, "offense_category_name": "Fraud Offenses", "offense_code": "26A"}, {"victim_id": 229676260, "vic_incident_id": 205998977, "victim_type_id": 4, "activity_type_id": NaN, "age_num": 56.0, "sex_code": "F", "data_year": 2024, "INCIDENT_ID": 205998977, "INCIDENT_DATE": "2024-12-08", "VICTIM_TYPE_NAME": "Individual", "RELATIONSHIP_NAME": "Victim Was Stranger", "victim_activity_at_incident": null, "offense_type_id": NaN, "offense_category_name": "Fraud Offenses", "offense_code": "26B"}, {"victim_id": 216154663, "vic_incident_id": 194216360, "victim_type_id": 4, "activity_type_id": NaN, "age_num": 29.0, "sex_code": "M", "data_year": 2024, "INCIDENT_ID": 194216360, "INCIDENT_DATE": "2024-03-19", "VICTIM_TYPE_NAME": "Individual", "RELATIONSHIP_NAME": "Victim was Otherwise Known", "victim_activity_at_incident": null, "offense_type_id": NaN, "offense_category_name": "Fraud Offenses", "offense_code": "26A"}, {"victim_id": 174715745, "vic_incident_id": 158044500, "victim_type_id": 4, "activity_type_id": NaN, "age_num": 57.0, "sex_code": "M", "data_year": 2022, "INCIDENT_ID": 158044500, "INCIDENT_DATE": "2022-07-22", "VICTIM_TYPE_NAME": "Individual", "RELATIONSHIP_NAME": "Victim was Otherwise Known", "victim_activity_at_incident": null, "offense_type_id": NaN, "offense_category_name": "Fraud Offenses", "offense_code": "26A"}, {"victim_id": 182913777, "vic_incident_id": 165211508, "victim_type_id": 4, "activity_type_id": NaN, "age_num": 32.0, "sex_code": "F", "data_year": 2022, "INCIDENT_ID": 165211508, "INCIDENT_DATE": "2022-08-01", "VICTIM_TYPE_NAME": "Individual", "RELATIONSHIP_NAME": "Victim Was Stranger", "victim_activity_at_incident": null, "offense_type_id": NaN, "offense_category_name": "Fraud Offenses", "offense_code": "26A"}, {"victim_id": 190384305, "vic_incident_id": 171728655, "victim_type_id": 4, "activity_type_id": NaN, "age_num": 30.0, "sex_code": "F", "data_year": 2023, "INCIDENT_ID": 171728655, "INCIDENT_DATE": "2023-04-09", "VICTIM_TYPE_NAME": "Individual", "RELATIONSHIP_NAME": "Victim Was Acquaintance", "victim_activity_at_incident": null, "offense_type_id": NaN, "offense_category_name": "Fraud Offenses", "offense_code": "26A"}, {"victim_id": 216701104, "vic_incident_id": 194689808, "victim_type_id": 4, "activity_type_id": NaN, "age_num": 60.0, "sex_code": "M", "data_year": 2024, "INCIDENT_ID": 194689808, "INCIDENT_DATE": "2024-04-09", "VICTIM_TYPE_NAME": "Individual", "RELATIONSHIP_NAME": "Victim Was Stranger", "victim_activity_at_incident": null, "offense_type_id": NaN, "offense_category_name": "Fraud Offenses", "offense_code": "26C"}, {"victim_id": 232121294, "vic_incident_id": 208138115, "victim_type_id": 4, "activity_type_id": NaN, "age_num": 36.0, "sex_code": "F", "data_year": 2024, "INCIDENT_ID": 208138115, "INCIDENT_DATE": "2024-06-24", "VICTIM_TYPE_NAME": "Individual", "RELATIONSHIP_NAME": "Victim Was Acquaintance", "victim_activity_at_incident": null, "offense_type_id": NaN, "offense_category_name": "Fraud Offenses", "offense_code": "26A"}, {"victim_id": 205159269, "vic_incident_id": 184644692, "victim_type_id": 4, "activity_type_id": NaN, "age_num": 56.0, "sex_code": "M", "data_year": 2023, "INCIDENT_ID": 184644692, "INCIDENT_DATE": "2023-10-06", "VICTIM_TYPE_NAME": "Individual", "RELATIONSHIP_NAME": "Victim Was Stranger", "victim_activity_at_incident": null, "offense_type_id": NaN, "offense_category_name": "Fraud Offenses", "offense_code": "26A"}, {"victim_id": 204973332, "vic_incident_id": 184482422, "victim_type_id": 4, "activity_type_id": NaN, "age_num": 69.0, "sex_code": "M", "data_year": 2023, "INCIDENT_ID": 184482422, "INCIDENT_DATE": "2023-12-29", "VICTIM_TYPE_NAME": "Individual", "RELATIONSHIP_NAME": "Victim Was Acquaintance", "victim_activity_at_incident": null, "offense_type_id": NaN, "offense_category_name": "Fraud Offenses", "offense_code": "26A"}, {"victim_id": 214355911, "vic_incident_id": 192651863, "victim_type_id": 4, "activity_type_id": NaN, "age_num": 43.0, "sex_code": "F", "data_year": 2024, "INCIDENT_ID": 192651863, "INCIDENT_DATE": "2024-02-22", "VICTIM_TYPE_NAME": "Individual", "RELATIONSHIP_NAME": "Victim Was Acquaintance", "victim_activity_at_incident": null, "offense_type_id": NaN, "offense_category_name": "Fraud Offenses", "offense_code": "26A"}, {"victim_id": 189817001, "vic_incident_id": 171233433, "victim_type_id": 4, "activity_type_id": NaN, "age_num": 80.0, "sex_code": "M", "data_year": 2023, "INCIDENT_ID": 171233433, "INCIDENT_DATE": "2023-01-03", "VICTIM_TYPE_NAME": "Individual", "RELATIONSHIP_NAME": "Victim Was Stranger", "victim_activity_at_incident": null, "offense_type_id": NaN, "offense_category_name": "Fraud Offenses", "offense_code": "26F"}, {"victim_id": 202436357, "vic_incident_id": 182271595, "victim_type_id": 4, "activity_type_id": NaN, "age_num": 22.0, "sex_code": "F", "data_year": 2023, "INCIDENT_ID": 182271595, "INCIDENT_DATE": "2023-09-24", "VICTIM_TYPE_NAME": "Individual", "RELATIONSHIP_NAME": "Victim Was Stranger", "victim_activity_at_incident": null, "offense_type_id": NaN, "offense_category_name": "Fraud Offenses", "offense_code": "26A"}, {"victim_id": 215305568, "vic_incident_id": 193479136, "victim_type_id": 4, "activity_type_id": NaN, "age_num": 43.0, "sex_code": "M", "data_year": 2024, "INCIDENT_ID": 193479136, "INCIDENT_DATE": "2024-02-23", "VICTIM_TYPE_NAME": "Individual", "RELATIONSHIP_NAME": "Victim Was Stranger", "victim_activity_at_incident": null, "offense_type_id": NaN, "offense_category_name": "Fraud Offenses", "offense_code": "26A"}, {"victim_id": 226804565, "vic_incident_id": 203489773, "victim_type_id": 4, "activity_type_id": NaN, "age_num": 53.0, "sex_code": "M", "data_year": 2024, "INCIDENT_ID": 203489773, "INCIDENT_DATE": "2024-12-22", "VICTIM_TYPE_NAME": "Individual", "RELATIONSHIP_NAME": "Victim Was Acquaintance", "victim_activity_at_incident": null, "offense_type_id": NaN, "offense_category_name": "Fraud Offenses", "offense_code": "26A"}, {"victim_id": 228216001, "vic_incident_id": 204720060, "victim_type_id": 4, "activity_type_id": NaN, "age_num": 20.0, "sex_code": "F", "data_year": 2024, "INCIDENT_ID": 204720060, "INCIDENT_DATE": "2024-12-01", "VICTIM_TYPE_NAME": "Individual", "RELATIONSHIP_NAME": "Victim Was Stranger", "victim_activity_at_incident": null, "offense_type_id": NaN, "offense_category_name": "Fraud Offenses", "offense_code": "26A"}, {"victim_id": 213677957, "vic_incident_id": 192061583, "victim_type_id": 4, "activity_type_id": NaN, "age_num": 19.0, "sex_code": "F", "data_year": 2024, "INCIDENT_ID": 192061583, "INCIDENT_DATE": "2024-01-01", "VICTIM_TYPE_NAME": "Individual", "RELATIONSHIP_NAME": "Victim was Employee", "victim_activity_at_incident": null, "offense_type_id": NaN, "offense_category_name": "Fraud Offenses", "offense_code": "26F"}, {"victim_id": 200145312, "vic_incident_id": 180278290, "victim_type_id": 4, "activity_type_id": NaN, "age_num": 64.0, "sex_code": "F", "data_year": 2023, "INCIDENT_ID": 180278290, "INCIDENT_DATE": "2023-09-28", "VICTIM_TYPE_NAME": "Individual", "RELATIONSHIP_NAME": "Victim Was Stranger", "victim_activity_at_incident": null, "offense_type_id": NaN, "offense_category_name": "Fraud Offenses", "offense_code": "26A"}, {"victim_id": 216038191, "vic_incident_id": 194116236, "victim_type_id": 4, "activity_type_id": NaN, "age_num": 55.0, "sex_code": "M", "data_year": 2024, "INCIDENT_ID": 194116236, "INCIDENT_DATE": "2024-07-10", "VICTIM_TYPE_NAME": "Individual", "RELATIONSHIP_NAME": "Victim Was Stranger", "victim_activity_at_incident": null, "offense_type_id": NaN, "offense_category_name": "Fraud Offenses", "offense_code": "26F"}, {"victim_id": 228810581, "vic_incident_id": 205245290, "victim_type_id": 4, "activity_type_id": NaN, "age_num": 31.0, "sex_code": "F", "data_year": 2024, "INCIDENT_ID": 205245290, "INCIDENT_DATE": "2024-07-17", "VICTIM_TYPE_NAME": "Individual", "RELATIONSHIP_NAME": "Victim Was Ex-Relationship (Ex-Boyfriend/Girlfriend)", "victim_activity_at_incident": null, "offense_type_id": NaN, "offense_category_name": "Fraud Offenses", "offense_code": "26A"}, {"victim_id": 201630325, "vic_incident_id": 181570124, "victim_type_id": 4, "activity_type_id": NaN, "age_num": 56.0, "sex_code": "M", "data_year": 2023, "INCIDENT_ID": 181570124, "INCIDENT_DATE": "2023-06-06", "VICTIM_TYPE_NAME": "Individual", "RELATIONSHIP_NAME": "Victim Was Stranger", "victim_activity_at_incident": null, "offense_type_id": NaN, "offense_category_name": "Fraud Offenses", "offense_code": "26A"}, {"victim_id": 205097854, "vic_incident_id": 184591385, "victim_type_id": 4, "activity_type_id": NaN, "age_num": 74.0, "sex_code": "F", "data_year": 2023, "INCIDENT_ID": 184591385, "INCIDENT_DATE": "2023-11-01", "VICTIM_TYPE_NAME": "Individual", "RELATIONSHIP_NAME": "Victim Was Acquaintance", "victim_activity_at_incident": null, "offense_type_id": NaN, "offense_category_name": "Fraud Offenses", "offense_code": "26A"}, {"victim_id": 203689264, "vic_incident_id": 183364045, "victim_type_id": 4, "activity_type_id": NaN, "age_num": 40.0, "sex_code": "M", "data_year": 2023, "INCIDENT_ID": 183364045, "INCIDENT_DATE": "2023-11-30", "VICTIM_TYPE_NAME": "Individual", "RELATIONSHIP_NAME": "Victim Was Sibling", "victim_activity_at_incident": null, "offense_type_id": NaN, "offense_category_name": "Fraud Offenses", "offense_code": "26F"}, {"victim_id": 161847073, "vic_incident_id": 146776125, "victim_type_id": 4, "activity_type_id": NaN, "age_num": 38.0, "sex_code": "F", "data_year": 2021, "INCIDENT_ID": 146776125, "INCIDENT_DATE": "2021-07-27", "VICTIM_TYPE_NAME": "Individual", "RELATIONSHIP_NAME": "Victim was Otherwise Known", "victim_activity_at_incident": null, "offense_type_id": NaN, "offense_category_name": "Fraud Offenses", "offense_code": "26A"}, {"victim_id": 174330715, "vic_incident_id": 157709037, "victim_type_id": 4, "activity_type_id": NaN, "age_num": 42.0, "sex_code": "M", "data_year": 2022, "INCIDENT_ID": 157709037, "INCIDENT_DATE": "2022-03-11", "VICTIM_TYPE_NAME": "Individual", "RELATIONSHIP_NAME": "Victim Was Acquaintance", "victim_activity_at_incident": null, "offense_type_id": NaN, "offense_category_name": "Fraud Offenses", "offense_code": "26F"}, {"victim_id": 227502253, "vic_incident_id": 204094056, "victim_type_id": 4, "activity_type_id": NaN, "age_num": 31.0, "sex_code": "F", "data_year": 2024, "INCIDENT_ID": 204094056, "INCIDENT_DATE": "2024-11-01", "VICTIM_TYPE_NAME": "Individual", "RELATIONSHIP_NAME": "Victim Was Stranger", "victim_activity_at_incident": null, "offense_type_id": NaN, "offense_category_name": "Fraud Offenses", "offense_code": "26A"}, {"victim_id": 148824677, "vic_incident_id": 135340770, "victim_type_id": 4, "activity_type_id": NaN, "age_num": 41.0, "sex_code": "M", "data_year": 2021, "INCIDENT_ID": 135340770, "INCIDENT_DATE": "2021-01-28", "VICTIM_TYPE_NAME": "Individual", "RELATIONSHIP_NAME": "Victim was Otherwise Known", "victim_activity_at_incident": null, "offense_type_id": NaN, "offense_category_name": "Fraud Offenses", "offense_code": "26A"}, {"victim_id": 193770892, "vic_incident_id": 174681240, "victim_type_id": 4, "activity_type_id": NaN, "age_num": 59.0, "sex_code": "F", "data_year": 2023, "INCIDENT_ID": 174681240, "INCIDENT_DATE": "2023-06-24", "VICTIM_TYPE_NAME": "Individual", "RELATIONSHIP_NAME": "Victim Was Ex-Relationship (Ex-Boyfriend/Girlfriend)", "victim_activity_at_incident": null, "offense_type_id": NaN, "offense_category_name": "Fraud Offenses", "offense_code": "26B"}, {"victim_id": 194092098, "vic_incident_id": 174963321, "victim_type_id": 4, "activity_type_id": NaN, "age_num": 18.0, "sex_code": "M", "data_year": 2023, "INCIDENT_ID": 174963321, "INCIDENT_DATE": "2023-07-23", "VICTIM_TYPE_NAME": "Individual", "RELATIONSHIP_NAME": "Victim Was Ex-Relationship (Ex-Boyfriend/Girlfriend)", "victim_activity_at_incident": null, "offense_type_id": NaN, "offense_category_name": "Fraud Offenses", "offense_code": "26A"}, {"victim_id": 158038786, "vic_incident_id": 143446230, "victim_type_id": 4, "activity_type_id": NaN, "age_num": 80.0, "sex_code": "M", "data_year": 2021, "INCIDENT_ID": 143446230, "INCIDENT_DATE": "2021-02-04", "VICTIM_TYPE_NAME": "Individual", "RELATIONSHIP_NAME": "Victim Was Stranger", "victim_activity_at_incident": null, "offense_type_id": NaN, "offense_category_name": "Fraud Offenses", "offense_code": "26F"}, {"victim_id": 228013380, "vic_incident_id": 204543808, "victim_type_id": 4, "activity_type_id": NaN, "age_num": 59.0, "sex_code": "F", "data_year": 2024, "INCIDENT_ID": 204543808, "INCIDENT_DATE": "2024-10-20", "VICTIM_TYPE_NAME": "Individual", "RELATIONSHIP_NAME": "Victim Was Stranger", "victim_activity_at_incident": null, "offense_type_id": NaN, "offense_category_name": "Fraud Offenses", "offense_code": "26A"}, {"victim_id": 216741704, "vic_incident_id": 194724454, "victim_type_id": 4, "activity_type_id": NaN, "age_num": 76.0, "sex_code": "F", "data_year": 2024, "INCIDENT_ID": 194724454, "INCIDENT_DATE": "2024-05-18", "VICTIM_TYPE_NAME": "Individual", "RELATIONSHIP_NAME": "Victim Was Stranger", "victim_activity_at_incident": null, "offense_type_id": NaN, "offense_category_name": "Fraud Offenses", "offense_code": "26A"}, {"victim_id": 200920445, "vic_incident_id": 180949786, "victim_type_id": 4, "activity_type_id": NaN, "age_num": 50.0, "sex_code": "F", "data_year": 2023, "INCIDENT_ID": 180949786, "INCIDENT_DATE": "2023-08-04", "VICTIM_TYPE_NAME": "Individual", "RELATIONSHIP_NAME": "Victim Was Stranger", "victim_activity_at_incident": null, "offense_type_id": NaN, "offense_category_name": "Fraud Offenses", "offense_code": "26A"}, {"victim_id": 206997860, "vic_incident_id": 186248204, "victim_type_id": 4, "activity_type_id": NaN, "age_num": 62.0, "sex_code": "M", "data_year": 2024, "INCIDENT_ID": 186248204, "INCIDENT_DATE": "2024-01-25", "VICTIM_TYPE_NAME": "Individual", "RELATIONSHIP_NAME": "Victim was Otherwise Known", "victim_activity_at_incident": null, "offense_type_id": NaN, "offense_category_name": "Fraud Offenses", "offense_code": "26C"}, {"victim_id": 226416627, "vic_incident_id": 203150919, "victim_type_id": 4, "activity_type_id": NaN, "age_num": 44.0, "sex_code": "M", "data_year": 2024, "INCIDENT_ID": 203150919, "INCIDENT_DATE": "2024-06-10", "VICTIM_TYPE_NAME": "Individual", "RELATIONSHIP_NAME": "Victim Was Stranger", "victim_activity_at_incident": null, "offense_type_id": NaN, "offense_category_name": "Fraud Offenses", "offense_code": "26A"}, {"victim_id": 227721466, "vic_incident_id": 204284699, "victim_type_id": 4, "activity_type_id": NaN, "age_num": 85.0, "sex_code": "M", "data_year": 2024, "INCIDENT_ID": 204284699, "INCIDENT_DATE": "2024-11-06", "VICTIM_TYPE_NAME": "Individual", "RELATIONSHIP_NAME": "Victim Was Stranger", "victim_activity_at_incident": null, "offense_type_id": NaN, "offense_category_name": "Fraud Offenses", "offense_code": "26A"}, {"victim_id": 223937781, "vic_incident_id": 200982795, "victim_type_id": 4, "activity_type_id": NaN, "age_num": 16.0, "sex_code": "F", "data_year": 2024, "INCIDENT_ID": 200982795, "INCIDENT_DATE": "2024-09-27", "VICTIM_TYPE_NAME": "Individual", "RELATIONSHIP_NAME": "Victim Was Acquaintance", "victim_activity_at_incident": null, "offense_type_id": NaN, "offense_category_name": "Fraud Offenses", "offense_code": "26C"}, {"victim_id": 207918483, "vic_incident_id": 187046728, "victim_type_id": 4, "activity_type_id": NaN, "age_num": 66.0, "sex_code": "M", "data_year": 2023, "INCIDENT_ID": 187046728, "INCIDENT_DATE": "2023-01-11", "VICTIM_TYPE_NAME": "Individual", "RELATIONSHIP_NAME": "Victim Was Parent", "victim_activity_at_incident": null, "offense_type_id": NaN, "offense_category_name": "Fraud Offenses", "offense_code": "26A"}, {"victim_id": 178080119, "vic_incident_id": 160981371, "victim_type_id": 4, "activity_type_id": NaN, "age_num": 57.0, "sex_code": "M", "data_year": 2022, "INCIDENT_ID": 160981371, "INCIDENT_DATE": "2022-09-07", "VICTIM_TYPE_NAME": "Individual", "RELATIONSHIP_NAME": "Victim Was Boyfriend/Girlfriend", "victim_activity_at_incident": null, "offense_type_id": NaN, "offense_category_name": "Fraud Offenses", "offense_code": "26A"}, {"victim_id": 182867416, "vic_incident_id": 165170593, "victim_type_id": 4, "activity_type_id": NaN, "age_num": 37.0, "sex_code": "F", "data_year": 2022, "INCIDENT_ID": 165170593, "INCIDENT_DATE": "2022-09-20", "VICTIM_TYPE_NAME": "Individual", "RELATIONSHIP_NAME": "Victim Was Stranger", "victim_activity_at_incident": null, "offense_type_id": NaN, "offense_category_name": "Fraud Offenses", "offense_code": "26A"}, {"victim_id": 195049960, "vic_incident_id": 175800148, "victim_type_id": 4, "activity_type_id": NaN, "age_num": 85.0, "sex_code": "F", "data_year": 2023, "INCIDENT_ID": 175800148, "INCIDENT_DATE": "2023-05-22", "VICTIM_TYPE_NAME": "Individual", "RELATIONSHIP_NAME": "Victim was Otherwise Known", "victim_activity_at_incident": null, "offense_type_id": NaN, "offense_category_name": "Fraud Offenses", "offense_code": "26A"}, {"victim_id": 221830814, "vic_incident_id": 199150079, "victim_type_id": 4, "activity_type_id": NaN, "age_num": 83.0, "sex_code": "F", "data_year": 2024, "INCIDENT_ID": 199150079, "INCIDENT_DATE": "2024-08-04", "VICTIM_TYPE_NAME": "Individual", "RELATIONSHIP_NAME": "Victim was Employer", "victim_activity_at_incident": null, "offense_type_id": NaN, "offense_category_name": "Fraud Offenses", "offense_code": "26F"}, {"victim_id": 164636759, "vic_incident_id": 149224917, "victim_type_id": 4, "activity_type_id": NaN, "age_num": 45.0, "sex_code": "F", "data_year": 2021, "INCIDENT_ID": 149224917, "INCIDENT_DATE": "2021-12-29", "VICTIM_TYPE_NAME": "Individual", "RELATIONSHIP_NAME": "Victim Was Stranger", "victim_activity_at_incident": null, "offense_type_id": NaN, "offense_category_name": "Fraud Offenses", "offense_code": "26A"}, {"victim_id": 161841845, "vic_incident_id": 146771593, "victim_type_id": 4, "activity_type_id": NaN, "age_num": 32.0, "sex_code": "M", "data_year": 2021, "INCIDENT_ID": 146771593, "INCIDENT_DATE": "2021-07-21", "VICTIM_TYPE_NAME": "Individual", "RELATIONSHIP_NAME": "Victim Was Ex-Relationship (Ex-Boyfriend/Girlfriend)", "victim_activity_at_incident": null, "offense_type_id": NaN, "offense_category_name": "Fraud Offenses", "offense_code": "26F"}, {"victim_id": 168307221, "vic_incident_id": 152449101, "victim_type_id": 4, "activity_type_id": NaN, "age_num": 56.0, "sex_code": "M", "data_year": 2022, "INCIDENT_ID": 152449101, "INCIDENT_DATE": "2022-02-24", "VICTIM_TYPE_NAME": "Individual", "RELATIONSHIP_NAME": "Victim was Otherwise Known", "victim_activity_at_incident": null, "offense_type_id": NaN, "offense_category_name": "Fraud Offenses", "offense_code": "26F"}, {"victim_id": 161872614, "vic_incident_id": 146798477, "victim_type_id": 4, "activity_type_id": NaN, "age_num": 61.0, "sex_code": "M", "data_year": 2021, "INCIDENT_ID": 146798477, "INCIDENT_DATE": "2021-08-20", "VICTIM_TYPE_NAME": "Individual", "RELATIONSHIP_NAME": "Victim Was Friend", "victim_activity_at_incident": null, "offense_type_id": NaN, "offense_category_name": "Fraud Offenses", "offense_code": "26F"}, {"victim_id": 176658601, "vic_incident_id": 159738961, "victim_type_id": 4, "activity_type_id": NaN, "age_num": 51.0, "sex_code": "F", "data_year": 2022, "INCIDENT_ID": 159738961, "INCIDENT_DATE": "2022-10-09", "VICTIM_TYPE_NAME": "Individual", "RELATIONSHIP_NAME": "Victim Was Ex-Relationship (Ex-Boyfriend/Girlfriend)", "victim_activity_at_incident": null, "offense_type_id": NaN, "offense_category_name": "Fraud Offenses", "offense_code": "26F"}, {"victim_id": 222584371, "vic_incident_id": 199804382, "victim_type_id": 4, "activity_type_id": NaN, "age_num": 42.0, "sex_code": "M", "data_year": 2024, "INCIDENT_ID": 199804382, "INCIDENT_DATE": "2024-08-07", "VICTIM_TYPE_NAME": "Individual", "RELATIONSHIP_NAME": "Victim was Otherwise Known", "victim_activity_at_incident": null, "offense_type_id": NaN, "offense_category_name": "Fraud Offenses", "offense_code": "26A"}, {"victim_id": 182444976, "vic_incident_id": 164800386, "victim_type_id": 4, "activity_type_id": NaN, "age_num": 73.0, "sex_code": "F", "data_year": 2022, "INCIDENT_ID": 164800386, "INCIDENT_DATE": "2022-09-20", "VICTIM_TYPE_NAME": "Individual", "RELATIONSHIP_NAME": "Victim Was Parent", "victim_activity_at_incident": null, "offense_type_id": NaN, "offense_category_name": "Fraud Offenses", "offense_code": "26A"}, {"victim_id": 182467897, "vic_incident_id": 164820388, "victim_type_id": 4, "activity_type_id": NaN, "age_num": 39.0, "sex_code": "F", "data_year": 2022, "INCIDENT_ID": 164820388, "INCIDENT_DATE": "2022-06-08", "VICTIM_TYPE_NAME": "Individual", "RELATIONSHIP_NAME": "Victim Was Acquaintance", "victim_activity_at_incident": null, "offense_type_id": NaN, "offense_category_name": "Fraud Offenses", "offense_code": "26A"}, {"victim_id": 228833104, "vic_incident_id": 205264859, "victim_type_id": 4, "activity_type_id": NaN, "age_num": 55.0, "sex_code": "F", "data_year": 2024, "INCIDENT_ID": 205264859, "INCIDENT_DATE": "2024-10-30", "VICTIM_TYPE_NAME": "Individual", "RELATIONSHIP_NAME": "Victim was Ex-Spouse", "victim_activity_at_incident": null, "offense_type_id": NaN, "offense_category_name": "Fraud Offenses", "offense_code": "26A"}, {"victim_id": 194702555, "vic_incident_id": 175497143, "victim_type_id": 4, "activity_type_id": NaN, "age_num": 36.0, "sex_code": "F", "data_year": 2023, "INCIDENT_ID": 175497143, "INCIDENT_DATE": "2023-06-03", "VICTIM_TYPE_NAME": "Individual", "RELATIONSHIP_NAME": "Victim Was Stranger", "victim_activity_at_incident": null, "offense_type_id": NaN, "offense_category_name": "Fraud Offenses", "offense_code": "26B"}, {"victim_id": 200836901, "vic_incident_id": 180876650, "victim_type_id": 4, "activity_type_id": NaN, "age_num": 16.0, "sex_code": "F", "data_year": 2023, "INCIDENT_ID": 180876650, "INCIDENT_DATE": "2023-05-09", "VICTIM_TYPE_NAME": "Individual", "RELATIONSHIP_NAME": "Victim Was Child", "victim_activity_at_incident": null, "offense_type_id": NaN, "offense_category_name": "Fraud Offenses", "offense_code": "26A"}, {"victim_id": 190474192, "vic_incident_id": 171807231, "victim_type_id": 4, "activity_type_id": NaN, "age_num": 62.0, "sex_code": "M", "data_year": 2023, "INCIDENT_ID": 171807231, "INCIDENT_DATE": "2023-02-28", "VICTIM_TYPE_NAME": "Individual", "RELATIONSHIP_NAME": "Victim Was Ex-Relationship (Ex-Boyfriend/Girlfriend)", "victim_activity_at_incident": null, "offense_type_id": NaN, "offense_category_name": "Fraud Offenses", "offense_code": "26A"}, {"victim_id": 182782171, "vic_incident_id": 165095346, "victim_type_id": 4, "activity_type_id": NaN, "age_num": 32.0, "sex_code": "M", "data_year": 2022, "INCIDENT_ID": 165095346, "INCIDENT_DATE": "2022-07-02", "VICTIM_TYPE_NAME": "Individual", "RELATIONSHIP_NAME": "Victim Was Other Family Member", "victim_activity_at_incident": null, "offense_type_id": NaN, "offense_category_name": "Fraud Offenses", "offense_code": "26F"}, {"victim_id": 181594454, "vic_incident_id": 164050487, "victim_type_id": 4, "activity_type_id": NaN, "age_num": 34.0, "sex_code": "M", "data_year": 2022, "INCIDENT_ID": 164050487, "INCIDENT_DATE": "2022-11-04", "VICTIM_TYPE_NAME": "Individual", "RELATIONSHIP_NAME": "Victim Was Neighbor", "victim_activity_at_incident": null, "offense_type_id": NaN, "offense_category_name": "Fraud Offenses", "offense_code": "26A"}, {"victim_id": 178861090, "vic_incident_id": 161665977, "victim_type_id": 4, "activity_type_id": NaN, "age_num": 59.0, "sex_code": "M", "data_year": 2022, "INCIDENT_ID": 161665977, "INCIDENT_DATE": "2022-01-01", "VICTIM_TYPE_NAME": "Individual", "RELATIONSHIP_NAME": "Victim Was Stranger", "victim_activity_at_incident": null, "offense_type_id": NaN, "offense_category_name": "Fraud Offenses", "offense_code": "26A"}, {"victim_id": 187005545, "vic_incident_id": 168780783, "victim_type_id": 4, "activity_type_id": NaN, "age_num": 39.0, "sex_code": "F", "data_year": 2023, "INCIDENT_ID": 168780783, "INCIDENT_DATE": "2023-03-24", "VICTIM_TYPE_NAME": "Individual", "RELATIONSHIP_NAME": "Victim Was Sibling", "victim_activity_at_incident": null, "offense_type_id": NaN, "offense_category_name": "Fraud Offenses", "offense_code": "26F"}, {"victim_id": 189816642, "vic_incident_id": 171233103, "victim_type_id": 4, "activity_type_id": NaN, "age_num": 82.0, "sex_code": "M", "data_year": 2023, "INCIDENT_ID": 171233103, "INCIDENT_DATE": "2023-01-25", "VICTIM_TYPE_NAME": "Individual", "RELATIONSHIP_NAME": "Victim Was Stranger", "victim_activity_at_incident": null, "offense_type_id": NaN, "offense_category_name": "Fraud Offenses", "offense_code": "26A"}, {"victim_id": 232230540, "vic_incident_id": 208232362, "victim_type_id": 4, "activity_type_id": NaN, "age_num": 28.0, "sex_code": "M", "data_year": 2024, "INCIDENT_ID": 208232362, "INCIDENT_DATE": "2024-07-04", "VICTIM_TYPE_NAME": "Individual", "RELATIONSHIP_NAME": "Victim Was Stranger", "victim_activity_at_incident": null, "offense_type_id": NaN, "offense_category_name": "Fraud Offenses", "offense_code": "26A"}, {"victim_id": 179944907, "vic_incident_id": 162610107, "victim_type_id": 4, "activity_type_id": NaN, "age_num": 66.0, "sex_code": "M", "data_year": 2022, "INCIDENT_ID": 162610107, "INCIDENT_DATE": "2022-08-25", "VICTIM_TYPE_NAME": "Individual", "RELATIONSHIP_NAME": "Victim Was Other Family Member", "victim_activity_at_incident": null, "offense_type_id": NaN, "offense_category_name": "Fraud Offenses", "offense_code": "26A"}, {"victim_id": 216726365, "vic_incident_id": 194711043, "victim_type_id": 4, "activity_type_id": NaN, "age_num": 37.0, "sex_code": "M", "data_year": 2024, "INCIDENT_ID": 194711043, "INCIDENT_DATE": "2024-05-13", "VICTIM_TYPE_NAME": "Individual", "RELATIONSHIP_NAME": "Victim Was Stranger", "victim_activity_at_incident": null, "offense_type_id": NaN, "offense_category_name": "Fraud Offenses", "offense_code": "26C"}, {"victim_id": 182135347, "vic_incident_id": 164530061, "victim_type_id": 4, "activity_type_id": NaN, "age_num": 59.0, "sex_code": "F", "data_year": 2022, "INCIDENT_ID": 164530061, "INCIDENT_DATE": "2022-04-30", "VICTIM_TYPE_NAME": "Individual", "RELATIONSHIP_NAME": "Victim Was Stranger", "victim_activity_at_incident": null, "offense_type_id": NaN, "offense_category_name": "Fraud Offenses", "offense_code": "26A"}, {"victim_id": 207390363, "vic_incident_id": 186587425, "victim_type_id": 4, "activity_type_id": NaN, "age_num": 45.0, "sex_code": "M", "data_year": 2023, "INCIDENT_ID": 186587425, "INCIDENT_DATE": "2023-10-05", "VICTIM_TYPE_NAME": "Individual", "RELATIONSHIP_NAME": "Victim Was Child of Boyfriend or Girlfriend", "victim_activity_at_incident": null, "offense_type_id": NaN, "offense_category_name": "Fraud Offenses", "offense_code": "26F"}, {"victim_id": 161782652, "vic_incident_id": 146720573, "victim_type_id": 4, "activity_type_id": NaN, "age_num": 47.0, "sex_code": "F", "data_year": 2021, "INCIDENT_ID": 146720573, "INCIDENT_DATE": "2021-07-08", "VICTIM_TYPE_NAME": "Individual", "RELATIONSHIP_NAME": "Victim Was Neighbor", "victim_activity_at_incident": null, "offense_type_id": NaN, "offense_category_name": "Fraud Offenses", "offense_code": "26B"}, {"victim_id": 171191104, "vic_incident_id": 154967099, "victim_type_id": 4, "activity_type_id": NaN, "age_num": 37.0, "sex_code": "F", "data_year": 2022, "INCIDENT_ID": 154967099, "INCIDENT_DATE": "2022-06-24", "VICTIM_TYPE_NAME": "Individual", "RELATIONSHIP_NAME": "Victim Was Boyfriend/Girlfriend", "victim_activity_at_incident": null, "offense_type_id": NaN, "offense_category_name": "Fraud Offenses", "offense_code": "26A"}, {"victim_id": 166169259, "vic_incident_id": 150571456, "victim_type_id": 4, "activity_type_id": NaN, "age_num": 20.0, "sex_code": "M", "data_year": 2021, "INCIDENT_ID": 150571456, "INCIDENT_DATE": "2021-05-08", "VICTIM_TYPE_NAME": "Individual", "RELATIONSHIP_NAME": "Victim Was Acquaintance", "victim_activity_at_incident": null, "offense_type_id": NaN, "offense_category_name": "Fraud Offenses", "offense_code": "26E"}, {"victim_id": 192228699, "vic_incident_id": 173330980, "victim_type_id": 4, "activity_type_id": NaN, "age_num": 49.0, "sex_code": "F", "data_year": 2023, "INCIDENT_ID": 173330980, "INCIDENT_DATE": "2023-05-25", "VICTIM_TYPE_NAME": "Individual", "RELATIONSHIP_NAME": "Victim Was Acquaintance", "victim_activity_at_incident": null, "offense_type_id": NaN, "offense_category_name": "Fraud Offenses", "offense_code": "26C"}, {"victim_id": 214099674, "vic_incident_id": 192430823, "victim_type_id": 5, "activity_type_id": 4.0, "age_num": 26.0, "sex_code": "M", "data_year": 2024, "INCIDENT_ID": 192430823, "INCIDENT_DATE": "2024-05-18", "VICTIM_TYPE_NAME": "Law Enforcement Officer", "RELATIONSHIP_NAME": "Victim Was Stranger", "victim_activity_at_incident": "Attempting Other Arrests", "offense_type_id": NaN, "offense_category_name": "Fraud Offenses", "offense_code": "26C"}, {"victim_id": 222830136, "vic_incident_id": 200020670, "victim_type_id": 4, "activity_type_id": NaN, "age_num": 72.0, "sex_code": "F", "data_year": 2024, "INCIDENT_ID": 200020670, "INCIDENT_DATE": "2024-10-10", "VICTIM_TYPE_NAME": "Individual", "RELATIONSHIP_NAME": "Victim was Otherwise Known", "victim_activity_at_incident": null, "offense_type_id": NaN, "offense_category_name": "Fraud Offenses", "offense_code": "26A"}, {"victim_id": 222997450, "vic_incident_id": 200165532, "victim_type_id": 4, "activity_type_id": NaN, "age_num": 25.0, "sex_code": "F", "data_year": 2024, "INCIDENT_ID": 200165532, "INCIDENT_DATE": "2024-01-26", "VICTIM_TYPE_NAME": "Individual", "RELATIONSHIP_NAME": "Victim Was Stranger", "victim_activity_at_incident": null, "offense_type_id": NaN, "offense_category_name": "Fraud Offenses", "offense_code": "26A"}, {"victim_id": 188547907, "vic_incident_id": 170123416, "victim_type_id": 4, "activity_type_id": NaN, "age_num": 79.0, "sex_code": "M", "data_year": 2023, "INCIDENT_ID": 170123416, "INCIDENT_DATE": "2023-02-18", "VICTIM_TYPE_NAME": "Individual", "RELATIONSHIP_NAME": "Victim was Otherwise Known", "victim_activity_at_incident": null, "offense_type_id": NaN, "offense_category_name": "Fraud Offenses", "offense_code": "26A"}, {"victim_id": 222638412, "vic_incident_id": 199852595, "victim_type_id": 4, "activity_type_id": NaN, "age_num": 32.0, "sex_code": "M", "data_year": 2024, "INCIDENT_ID": 199852595, "INCIDENT_DATE": "2024-09-08", "VICTIM_TYPE_NAME": "Individual", "RELATIONSHIP_NAME": "Victim Was Stranger", "victim_activity_at_incident": null, "offense_type_id": NaN, "offense_category_name": "Fraud Offenses", "offense_code": "26C"}, {"victim_id": 189836139, "vic_incident_id": 171249987, "victim_type_id": 4, "activity_type_id": NaN, "age_num": 66.0, "sex_code": "M", "data_year": 2023, "INCIDENT_ID": 171249987, "INCIDENT_DATE": "2023-02-05", "VICTIM_TYPE_NAME": "Individual", "RELATIONSHIP_NAME": "Victim was Otherwise Known", "victim_activity_at_incident": null, "offense_type_id": NaN, "offense_category_name": "Fraud Offenses", "offense_code": "26F"}, {"victim_id": 229257394, "vic_incident_id": 205633962, "victim_type_id": 4, "activity_type_id": NaN, "age_num": 54.0, "sex_code": "M", "data_year": 2024, "INCIDENT_ID": 205633962, "INCIDENT_DATE": "2024-06-27", "VICTIM_TYPE_NAME": "Individual", "RELATIONSHIP_NAME": "Victim Was Acquaintance", "victim_activity_at_incident": null, "offense_type_id": NaN, "offense_category_name": "Fraud Offenses", "offense_code": "26A"}, {"victim_id": 225111097, "vic_incident_id": 202004296, "victim_type_id": 4, "activity_type_id": NaN, "age_num": 80.0, "sex_code": "M", "data_year": 2024, "INCIDENT_ID": 202004296, "INCIDENT_DATE": "2024-04-19", "VICTIM_TYPE_NAME": "Individual", "RELATIONSHIP_NAME": "Victim Was In-law", "victim_activity_at_incident": null, "offense_type_id": NaN, "offense_category_name": "Fraud Offenses", "offense_code": "26A"}, {"victim_id": 171732861, "vic_incident_id": 155442078, "victim_type_id": 4, "activity_type_id": NaN, "age_num": 30.0, "sex_code": "M", "data_year": 2022, "INCIDENT_ID": 155442078, "INCIDENT_DATE": "2022-05-23", "VICTIM_TYPE_NAME": "Individual", "RELATIONSHIP_NAME": "Victim Was Stranger", "victim_activity_at_incident": null, "offense_type_id": NaN, "offense_category_name": "Fraud Offenses", "offense_code": "26C"}, {"victim_id": 195176161, "vic_incident_id": 175910116, "victim_type_id": 4, "activity_type_id": NaN, "age_num": 45.0, "sex_code": "M", "data_year": 2023, "INCIDENT_ID": 175910116, "INCIDENT_DATE": "2023-01-07", "VICTIM_TYPE_NAME": "Individual", "RELATIONSHIP_NAME": "Victim Was Stranger", "victim_activity_at_incident": null, "offense_type_id": NaN, "offense_category_name": "Fraud Offenses", "offense_code": "26A"}, {"victim_id": 163266351, "vic_incident_id": 148024064, "victim_type_id": 4, "activity_type_id": NaN, "age_num": 63.0, "sex_code": "M", "data_year": 2021, "INCIDENT_ID": 148024064, "INCIDENT_DATE": "2021-11-30", "VICTIM_TYPE_NAME": "Individual", "RELATIONSHIP_NAME": "Victim Was Stranger", "victim_activity_at_incident": null, "offense_type_id": NaN, "offense_category_name": "Fraud Offenses", "offense_code": "26A"}, {"victim_id": 189779481, "vic_incident_id": 171200681, "victim_type_id": 4, "activity_type_id": NaN, "age_num": 26.0, "sex_code": "M", "data_year": 2023, "INCIDENT_ID": 171200681, "INCIDENT_DATE": "2023-01-10", "VICTIM_TYPE_NAME": "Individual", "RELATIONSHIP_NAME": "Victim Was Ex-Relationship (Ex-Boyfriend/Girlfriend)", "victim_activity_at_incident": null, "offense_type_id": NaN, "offense_category_name": "Fraud Offenses", "offense_code": "26F"}, {"victim_id": 204866743, "vic_incident_id": 184390169, "victim_type_id": 4, "activity_type_id": NaN, "age_num": 41.0, "sex_code": "F", "data_year": 2023, "INCIDENT_ID": 184390169, "INCIDENT_DATE": "2023-12-04", "VICTIM_TYPE_NAME": "Individual", "RELATIONSHIP_NAME": "Victim Was Acquaintance", "victim_activity_at_incident": null, "offense_type_id": NaN, "offense_category_name": "Fraud Offenses", "offense_code": "26F"}, {"victim_id": 201410278, "vic_incident_id": 181377857, "victim_type_id": 4, "activity_type_id": NaN, "age_num": 46.0, "sex_code": "M", "data_year": 2023, "INCIDENT_ID": 181377857, "INCIDENT_DATE": "2023-10-31", "VICTIM_TYPE_NAME": "Individual", "RELATIONSHIP_NAME": "Victim Was Acquaintance", "victim_activity_at_incident": null, "offense_type_id": NaN, "offense_category_name": "Fraud Offenses", "offense_code": "26A"}, {"victim_id": 164648365, "vic_incident_id": 149235005, "victim_type_id": 4, "activity_type_id": NaN, "age_num": 24.0, "sex_code": "F", "data_year": 2021, "INCIDENT_ID": 149235005, "INCIDENT_DATE": "2021-10-15", "VICTIM_TYPE_NAME": "Individual", "RELATIONSHIP_NAME": "Victim was Otherwise Known", "victim_activity_at_incident": null, "offense_type_id": NaN, "offense_category_name": "Fraud Offenses", "offense_code": "26F"}, {"victim_id": 223075856, "vic_incident_id": 200235136, "victim_type_id": 4, "activity_type_id": NaN, "age_num": 41.0, "sex_code": "F", "data_year": 2024, "INCIDENT_ID": 200235136, "INCIDENT_DATE": "2024-01-16", "VICTIM_TYPE_NAME": "Individual", "RELATIONSHIP_NAME": "Victim Was Stranger", "victim_activity_at_incident": null, "offense_type_id": NaN, "offense_category_name": "Fraud Offenses", "offense_code": "26A"}, {"victim_id": 178069795, "vic_incident_id": 160972582, "victim_type_id": 4, "activity_type_id": NaN, "age_num": 75.0, "sex_code": "F", "data_year": 2022, "INCIDENT_ID": 160972582, "INCIDENT_DATE": "2022-10-19", "VICTIM_TYPE_NAME": "Individual", "RELATIONSHIP_NAME": "Victim Was Stranger", "victim_activity_at_incident": null, "offense_type_id": NaN, "offense_category_name": "Fraud Offenses", "offense_code": "26A"}, {"victim_id": 217816172, "vic_incident_id": 195661333, "victim_type_id": 4, "activity_type_id": NaN, "age_num": 72.0, "sex_code": "M", "data_year": 2024, "INCIDENT_ID": 195661333, "INCIDENT_DATE": "2024-07-01", "VICTIM_TYPE_NAME": "Individual", "RELATIONSHIP_NAME": "Victim Was Ex-Relationship (Ex-Boyfriend/Girlfriend)", "victim_activity_at_incident": null, "offense_type_id": NaN, "offense_category_name": "Fraud Offenses", "offense_code": "26A"}, {"victim_id": 198193368, "vic_incident_id": 178541304, "victim_type_id": 4, "activity_type_id": NaN, "age_num": 61.0, "sex_code": "M", "data_year": 2023, "INCIDENT_ID": 178541304, "INCIDENT_DATE": "2023-04-19", "VICTIM_TYPE_NAME": "Individual", "RELATIONSHIP_NAME": "Victim Was Acquaintance", "victim_activity_at_incident": null, "offense_type_id": NaN, "offense_category_name": "Fraud Offenses", "offense_code": "26B"}, {"victim_id": 195258634, "vic_incident_id": 175981193, "victim_type_id": 4, "activity_type_id": NaN, "age_num": 25.0, "sex_code": "F", "data_year": 2023, "INCIDENT_ID": 175981193, "INCIDENT_DATE": "2023-07-02", "VICTIM_TYPE_NAME": "Individual", "RELATIONSHIP_NAME": "Victim Was Sibling", "victim_activity_at_incident": null, "offense_type_id": NaN, "offense_category_name": "Fraud Offenses", "offense_code": "26B"}, {"victim_id": 181270775, "vic_incident_id": 163766351, "victim_type_id": 4, "activity_type_id": NaN, "age_num": 51.0, "sex_code": "F", "data_year": 2022, "INCIDENT_ID": 163766351, "INCIDENT_DATE": "2022-03-22", "VICTIM_TYPE_NAME": "Individual", "RELATIONSHIP_NAME": "Victim Was Stranger", "victim_activity_at_incident": null, "offense_type_id": NaN, "offense_category_name": "Fraud Offenses", "offense_code": "26B"}, {"victim_id": 174330752, "vic_incident_id": 157709074, "victim_type_id": 4, "activity_type_id": NaN, "age_num": 81.0, "sex_code": "M", "data_year": 2022, "INCIDENT_ID": 157709074, "INCIDENT_DATE": "2022-04-26", "VICTIM_TYPE_NAME": "Individual", "RELATIONSHIP_NAME": "Victim Was Stranger", "victim_activity_at_incident": null, "offense_type_id": NaN, "offense_category_name": "Fraud Offenses", "offense_code": "26E"}, {"victim_id": 182467032, "vic_incident_id": 164819635, "victim_type_id": 4, "activity_type_id": NaN, "age_num": 68.0, "sex_code": "F", "data_year": 2022, "INCIDENT_ID": 164819635, "INCIDENT_DATE": "2022-12-07", "VICTIM_TYPE_NAME": "Individual", "RELATIONSHIP_NAME": "Victim Was Acquaintance", "victim_activity_at_incident": null, "offense_type_id": NaN, "offense_category_name": "Fraud Offenses", "offense_code": "26A"}, {"victim_id": 219488866, "vic_incident_id": 197111228, "victim_type_id": 4, "activity_type_id": NaN, "age_num": 72.0, "sex_code": "M", "data_year": 2024, "INCIDENT_ID": 197111228, "INCIDENT_DATE": "2024-07-19", "VICTIM_TYPE_NAME": "Individual", "RELATIONSHIP_NAME": "Victim Was Stranger", "victim_activity_at_incident": null, "offense_type_id": NaN, "offense_category_name": "Fraud Offenses", "offense_code": "26F"}, {"victim_id": 149046975, "vic_incident_id": 135582501, "victim_type_id": 4, "activity_type_id": NaN, "age_num": 67.0, "sex_code": "M", "data_year": 2020, "INCIDENT_ID": 135582501, "INCIDENT_DATE": "22-SEP-20", "VICTIM_TYPE_NAME": "Individual", "RELATIONSHIP_NAME": "Victim Was Acquaintance", "victim_activity_at_incident": null, "offense_type_id": 2.0, "offense_category_name": "Fraud Offenses", "offense_code": null}, {"victim_id": 222425619, "vic_incident_id": 199666406, "victim_type_id": 4, "activity_type_id": NaN, "age_num": 22.0, "sex_code": "F", "data_year": 2024, "INCIDENT_ID": 199666406, "INCIDENT_DATE": "2024-09-12", "VICTIM_TYPE_NAME": "Individual", "RELATIONSHIP_NAME": "Victim Was Child", "victim_activity_at_incident": null, "offense_type_id": NaN, "offense_category_name": "Fraud Offenses", "offense_code": "26C"}]}]}